BookingLibrary/__init__.py
BookingLibrary/bookingmanagement.py
BookingLibrary-0.1.0.dist-info/LICENSE.txt
BookingLibrary-0.1.0.dist-info/METADATA
BookingLibrary-0.1.0.dist-info/WHEEL
BookingLibrary-0.1.0.dist-info/top_level.txt
BookingLibrary-0.1.0.dist-info/RECORD
