Metadata-Version: 2.1
Name: BookingLibrary
Version: 0.1.0
Summary: A simple booking management system.
Home-page: 
Author: Mageshwaran
Author-email: mageshwaran960@gmail.com
Classifier: Programming Language :: Python :: 3
Classifier: License :: OSI Approved :: MIT License
Classifier: Operating System :: OS Independent
Requires-Python: >=3.6
License-File: LICENSE.txt
